{"date_time":"2025-04-21T10:53:26.937957415Z","solver":"MathSAT","arguments":null,"hash_function":"SHA224","rounds":9,"collision_type":"Standard","execution_time":{"secs":0,"nanos":286590432},"memory_bytes":39391232,"result":"Sat","console_output":["sat\n( (a0 (_ bv3238371032 32))\n  (b0 (_ bv914150663 32))\n  (c0 (_ bv812702999 32))\n  (d0 (_ bv4144912697 32))\n  (e0 (_ bv4290775857 32))\n  (f0 (_ bv1750603025 32))\n  (g0 (_ bv1694076839 32))\n  (h0 (_ bv3204075428 32)) )\n( (m0_hash0 (_ bv250406178 32))\n  (m0_hash1 (_ bv4246736106 32))\n  (m0_hash2 (_ bv3422834059 32))\n  (m0_hash3 (_ bv1445143493 32))\n  (m0_hash4 (_ bv3649754835 32))\n  (m0_hash5 (_ bv1181671662 32))\n  (m0_hash6 (_ bv1118258986 32)) )\n( (a0 (_ bv3238371032 32))\n  (e0 (_ bv4290775857 32))\n  (m0_w0 (_ bv2520349702 32))\n  (m1_w0 (_ bv952621583 32))\n  (m0_a1 (_ bv1131268960 32))\n  (m1_a1 (_ bv3858508137 32))\n  (m0_e1 (_ bv957037284 32))\n  (m1_e1 (_ bv3684276461 32))\n  (m0_w1 (_ bv4175184008 32))\n  (m1_w1 (_ bv458404697 32))\n  (m0_a2 (_ bv3535694716 32))\n  (m1_a2 (_ bv4218361844 32))\n  (m0_e2 (_ bv3268182168 32))\n  (m1_e2 (_ bv2211304854 32))\n  (m0_w2 (_ bv2795898956 32))\n  (m1_w2 (_ bv667153932 32))\n  (m0_a3 (_ bv1915557022 32))\n  (m1_a3 (_ bv1915557022 32))\n  (m0_e3 (_ bv1318527431 32))\n  (m1_e3 (_ bv2316893253 32))\n  (m0_w3 (_ bv1978167001 32))\n  (m1_w3 (_ bv1342658022 32))\n  (m0_a4 (_ bv528865046 32))\n  (m1_a4 (_ bv528865046 32))\n  (m0_e4 (_ bv36928747 32))\n  (m1_e4 (_ bv1626583659 32))\n  (m0_w4 (_ bv1426893653 32))\n  (m1_w4 (_ bv1499549920 32))\n  (m0_a5 (_ bv769683511 32))\n  (m1_a5 (_ bv769683511 32))\n  (m0_e5 (_ bv4136833764 32))\n  (m1_e5 (_ bv1889644661 32))\n  (m0_w5 (_ bv2798327295 32))\n  (m1_w5 (_ bv4209286 32))\n  (m0_a6 (_ bv1595198092 32))\n  (m1_a6 (_ bv1595198092 32))\n  (m0_e6 (_ bv657207865 32))\n  (m1_e6 (_ bv1339874993 32))\n  (m0_w6 (_ bv787830203 32))\n  (m1_w6 (_ bv4044006203 32))\n  (m0_a7 (_ bv2610131060 32))\n  (m1_a7 (_ bv2610131060 32))\n  (m0_e7 (_ bv3719149443 32))\n  (m1_e7 (_ bv3719149443 32))\n  (m0_w7 (_ bv3224118300 32))\n  (m1_w7 (_ bv454920716 32))\n  (m0_a8 (_ bv3332585443 32))\n  (m1_a8 (_ bv3332585443 32))\n  (m0_e8 (_ bv3726035933 32))\n  (m1_e8 (_ bv3726035933 32))\n  (m0_w8 (_ bv3632034613 32))\n  (m1_w8 (_ bv2110648740 32)) )\n","\tCommand being timed: \"./solvers/mathsat smt/SHA224_STD_9.smt2\"\n\tUser time (seconds): 0.26\n\tSystem time (seconds): 0.01\n\tPercent of CPU this job got: 99%\n\tElapsed (wall clock) time (h:mm:ss or m:ss): 0:00.28\n\tAverage shared text size (kbytes): 0\n\tAverage unshared data size (kbytes): 0\n\tAverage stack size (kbytes): 0\n\tAverage total size (kbytes): 0\n\tMaximum resident set size (kbytes): 38468\n\tAverage resident set size (kbytes): 0\n\tMajor (requiring I/O) page faults: 0\n\tMinor (reclaiming a frame) page faults: 8507\n\tVoluntary context switches: 1\n\tInvoluntary context switches: 22\n\tSwaps: 0\n\tFile system inputs: 0\n\tFile system outputs: 0\n\tSocket messages sent: 0\n\tSocket messages received: 0\n\tSignals delivered: 0\n\tPage size (bytes): 4096\n\tExit status: 0\n"],"is_valid":null,"is_baseline":true,"is_rerun":false,"encoding":{"BruteForce":{"simplified_maj_and_ch_functions":false,"alternative_add":false}},"stop_tolerance":0,"timeout":{"secs":900,"nanos":0}}